[
  [
    {
      "name": "未启动软件",
      "xAxis": "0"
    },
    {
      "xAxis": "15"
    }
  ],
  [
    {
      "name": "打开软件，进入主页",
      "xAxis": "15"
    },
    {
      "xAxis": "22"
    }
  ],
  [
    {
      "name": "进入VR界面，选择视频播放",
      "xAxis": "22"
    },
    {
      "xAxis": "48"
    }
  ],
  [
    {
      "name": "视频播放",
      "xAxis": "48"
    },
    {
      "xAxis": "130"
    }
  ],
  [
    {
      "name": "回到软件主页,无操作",
      "xAxis": "130"
    },
    {
      "xAxis": "145"
    }
  ],
  [
    {
      "name": "退出软件，回到手机界面，无操作",
      "xAxis": "145"
    },
    {
      "xAxis": "160"
    }
  ]
]
